{
  "name": "Miran, Stephen I",
  "slug": "miran-stephen",
  "title": "Chairman, Council of Economic Advisers",
  "agency": "Council of Economic Advisers",
  "level": "Sub-Cabinet",
  "filingType": "278-T Periodic Transaction Report",
  "mostRecentFilingDate": "2025-12-03",
  "transactions": [
    {
      "description": "ISHARES S&P 500 INDEX FUND",
      "ticker": "IVV",
      "type": "Purchase",
      "date": "2025-11-14",
      "amount": "$500,001-$1,000,000",
      "lateFilingFlag": false
    },
    {
      "description": "Abbott Laboratories",
      "ticker": null,
      "type": "Sale",
      "date": "2025-06-09",
      "amount": "$15,001-$50,000",
      "lateFilingFlag": false
    },
    {
      "description": "Adobe Inc",
      "ticker": null,
      "type": "Sale",
      "date": "2025-06-09",
      "amount": "$50,001-$100,000",
      "lateFilingFlag": false
    },
    {
      "description": "Advanced Drainage System Inc.",
      "ticker": null,
      "type": "Sale",
      "date": "2025-06-09",
      "amount": "$15,001-$50,000",
      "lateFilingFlag": false
    },
    {
      "description": "Alcon Inc.",
      "ticker": null,
      "type": "Sale",
      "date": "2025-06-09",
      "amount": "$50,001-$100,000",
      "lateFilingFlag": false
    },
    {
      "description": "Alphabet Inc.",
      "ticker": "GOOGL",
      "type": "Sale",
      "date": "2025-06-09",
      "amount": "$100,001-$250,000",
      "lateFilingFlag": false
    },
    {
      "description": "Amazon.com Inc.",
      "ticker": "AMZN",
      "type": "Sale",
      "date": "2025-06-09",
      "amount": "$50,001-$100,000",
      "lateFilingFlag": false
    },
    {
      "description": "Applied Materials Inc.",
      "ticker": null,
      "type": "Sale",
      "date": "2025-06-09",
      "amount": "$15,001-$50,000",
      "lateFilingFlag": false
    },
    {
      "description": "AptaraGroup Inc.",
      "ticker": null,
      "type": "Sale",
      "date": "2025-06-09",
      "amount": "$15,001-$50,000",
      "lateFilingFlag": false
    },
    {
      "description": "Arista Networks Inc.",
      "ticker": null,
      "type": "Sale",
      "date": "2025-06-09",
      "amount": "$15,001-$50,000",
      "lateFilingFlag": false
    },
    {
      "description": "Arthur J. Gallagher & Co.",
      "ticker": null,
      "type": "Sale",
      "date": "2025-06-09",
      "amount": "$50,001-$100,000",
      "lateFilingFlag": false
    },
    {
      "description": "Automatic Data Processing Inc.",
      "ticker": null,
      "type": "Sale",
      "date": "2025-06-09",
      "amount": "$15,001-$50,000",
      "lateFilingFlag": false
    },
    {
      "description": "Berkshire Hathaway Inc.",
      "ticker": "BRK.B",
      "type": "Sale",
      "date": "2025-06-09",
      "amount": "$100,001-$250,000",
      "lateFilingFlag": false
    },
    {
      "description": "Booking Holdings Inc.",
      "ticker": null,
      "type": "Sale",
      "date": "2025-06-09",
      "amount": "$50,001-$100,000",
      "lateFilingFlag": false
    },
    {
      "description": "Bright Horizons Family Solutions",
      "ticker": null,
      "type": "Sale",
      "date": "2025-06-09",
      "amount": "$15,001-$50,000",
      "lateFilingFlag": false
    },
    {
      "description": "Brown & Brown Inc.",
      "ticker": null,
      "type": "Sale",
      "date": "2025-06-09",
      "amount": "$15,001-$50,000",
      "lateFilingFlag": false
    },
    {
      "description": "Bruker Corp",
      "ticker": null,
      "type": "Sale",
      "date": "2025-06-09",
      "amount": "$15,001-$50,000",
      "lateFilingFlag": false
    },
    {
      "description": "Cadence Design Systems Inc.",
      "ticker": null,
      "type": "Sale",
      "date": "2025-06-09",
      "amount": "$15,001-$50,000",
      "lateFilingFlag": false
    },
    {
      "description": "CBRE Group",
      "ticker": null,
      "type": "Sale",
      "date": "2025-06-09",
      "amount": "$15,001-$50,000",
      "lateFilingFlag": false
    },
    {
      "description": "Costco Wholesale Corp",
      "ticker": null,
      "type": "Sale",
      "date": "2025-06-09",
      "amount": "$50,001-$100,000",
      "lateFilingFlag": false
    },
    {
      "description": "Darling Ingredients Inc.",
      "ticker": null,
      "type": "Sale",
      "date": "2025-06-09",
      "amount": "$15,001-$50,000",
      "lateFilingFlag": false
    },
    {
      "description": "Entegris Inc",
      "ticker": null,
      "type": "Sale",
      "date": "2025-06-09",
      "amount": "$15,001-$50,000",
      "lateFilingFlag": false
    },
    {
      "description": "GFL Environmental",
      "ticker": null,
      "type": "Sale",
      "date": "2025-06-09",
      "amount": "$15,001-$50,000",
      "lateFilingFlag": false
    },
    {
      "description": "Globant SA",
      "ticker": null,
      "type": "Sale",
      "date": "2025-06-09",
      "amount": "$15,001-$50,000",
      "lateFilingFlag": false
    },
    {
      "description": "Guidewire Software Inc",
      "ticker": null,
      "type": "Sale",
      "date": "2025-06-09",
      "amount": "$50,001-$100,000",
      "lateFilingFlag": false
    },
    {
      "description": "GXO Logistics Incorporated",
      "ticker": null,
      "type": "Sale",
      "date": "2025-06-09",
      "amount": "$15,001-$50,000",
      "lateFilingFlag": false
    },
    {
      "description": "Heico Corp",
      "ticker": null,
      "type": "Sale",
      "date": "2025-06-09",
      "amount": "$15,001-$50,000",
      "lateFilingFlag": false
    },
    {
      "description": "Icon PLC",
      "ticker": null,
      "type": "Sale",
      "date": "2025-06-09",
      "amount": "$15,001-$50,000",
      "lateFilingFlag": false
    },
    {
      "description": "KLA Corporation",
      "ticker": null,
      "type": "Sale",
      "date": "2025-06-09",
      "amount": "$100,001-$250,000",
      "lateFilingFlag": false
    },
    {
      "description": "Linde PLC",
      "ticker": null,
      "type": "Sale",
      "date": "2025-06-09",
      "amount": "$100,001-$250,000",
      "lateFilingFlag": false
    },
    {
      "description": "LPL Financial Holdings Inc",
      "ticker": null,
      "type": "Sale",
      "date": "2025-06-09",
      "amount": "$15,001-$50,000",
      "lateFilingFlag": false
    },
    {
      "description": "Mastercard Incorporated",
      "ticker": null,
      "type": "Sale",
      "date": "2025-06-09",
      "amount": "$100,001-$250,000",
      "lateFilingFlag": false
    },
    {
      "description": "Microsoft Corp",
      "ticker": "MSFT",
      "type": "Sale",
      "date": "2025-06-09",
      "amount": "$100,001-$250,000",
      "lateFilingFlag": false
    },
    {
      "description": "Nike Inc.",
      "ticker": null,
      "type": "Sale",
      "date": "2025-06-09",
      "amount": "$15,001-$50,000",
      "lateFilingFlag": false
    },
    {
      "description": "Oracle Corp.",
      "ticker": null,
      "type": "Sale",
      "date": "2025-06-09",
      "amount": "$100,001-$250,000",
      "lateFilingFlag": false
    },
    {
      "description": "Otis Worldwide Corporation",
      "ticker": null,
      "type": "Sale",
      "date": "2025-06-09",
      "amount": "$15,001-$50,000",
      "lateFilingFlag": false
    },
    {
      "description": "Progressive Corp Ohio",
      "ticker": null,
      "type": "Sale",
      "date": "2025-06-09",
      "amount": "$15,001-$50,000",
      "lateFilingFlag": false
    },
    {
      "description": "S&P Global Inc",
      "ticker": null,
      "type": "Sale",
      "date": "2025-06-09",
      "amount": "$50,001-$100,000",
      "lateFilingFlag": false
    },
    {
      "description": "Shift4 Payments Inc.",
      "ticker": null,
      "type": "Sale",
      "date": "2025-06-09",
      "amount": "$15,001-$50,000",
      "lateFilingFlag": false
    },
    {
      "description": "Take-Two Interactive Software",
      "ticker": null,
      "type": "Sale",
      "date": "2025-06-09",
      "amount": "$15,001-$50,000",
      "lateFilingFlag": false
    },
    {
      "description": "Texas Instruments Inc",
      "ticker": null,
      "type": "Sale",
      "date": "2025-06-09",
      "amount": "$50,001-$100,000",
      "lateFilingFlag": false
    },
    {
      "description": "Thermo Fisher Scientific Inc.",
      "ticker": null,
      "type": "Sale",
      "date": "2025-06-09",
      "amount": "$15,001-$50,000",
      "lateFilingFlag": false
    },
    {
      "description": "Toro Co",
      "ticker": null,
      "type": "Sale",
      "date": "2025-06-09",
      "amount": "$1,001-$15,000",
      "lateFilingFlag": false
    },
    {
      "description": "ULSolutions Inc.",
      "ticker": null,
      "type": "Sale",
      "date": "2025-06-09",
      "amount": "$15,001-$50,000",
      "lateFilingFlag": false
    },
    {
      "description": "United Health Group",
      "ticker": null,
      "type": "Sale",
      "date": "2025-06-09",
      "amount": "$15,001-$50,000",
      "lateFilingFlag": false
    },
    {
      "description": "Vulcan Materials Co.",
      "ticker": null,
      "type": "Sale",
      "date": "2025-06-09",
      "amount": "$15,001-$50,000",
      "lateFilingFlag": false
    },
    {
      "description": "Waste Management Inc.",
      "ticker": null,
      "type": "Sale",
      "date": "2025-06-09",
      "amount": "$100,001-$250,000",
      "lateFilingFlag": false
    },
    {
      "description": "Watsco Inc",
      "ticker": null,
      "type": "Sale",
      "date": "2025-06-09",
      "amount": "$15,001-$50,000",
      "lateFilingFlag": false
    },
    {
      "description": "West Pharmaceutical Services Inc.",
      "ticker": null,
      "type": "Sale",
      "date": "2025-06-09",
      "amount": "$15,001-$50,000",
      "lateFilingFlag": false
    },
    {
      "description": "Willscot Mobile Mini Holdings Co.",
      "ticker": null,
      "type": "Sale",
      "date": "2025-06-09",
      "amount": "$1,001-$15,000",
      "lateFilingFlag": false
    },
    {
      "description": "Wyndham Hotels & Resorts Inc",
      "ticker": null,
      "type": "Sale",
      "date": "2025-06-09",
      "amount": "$15,001-$50,000",
      "lateFilingFlag": false
    },
    {
      "description": "Zebra Technologies Corp.",
      "ticker": null,
      "type": "Sale",
      "date": "2025-06-09",
      "amount": "$15,001-$50,000",
      "lateFilingFlag": false
    },
    {
      "description": "Zoetis Inc",
      "ticker": null,
      "type": "Sale",
      "date": "2025-06-09",
      "amount": "$50,001-$100,000",
      "lateFilingFlag": false
    },
    {
      "description": "Eli Lilly & Co.",
      "ticker": null,
      "type": "Sale",
      "date": "2025-06-09",
      "amount": "$1,001-$15,000",
      "lateFilingFlag": false
    },
    {
      "description": "Keysight Technologies Inc.",
      "ticker": null,
      "type": "Sale",
      "date": "2025-06-09",
      "amount": "$15,001-$50,000",
      "lateFilingFlag": false
    },
    {
      "description": "Novo Nordisk",
      "ticker": null,
      "type": "Sale",
      "date": "2025-06-09",
      "amount": "$1,001-$15,000",
      "lateFilingFlag": false
    },
    {
      "description": "NVR Inc.",
      "ticker": null,
      "type": "Sale",
      "date": "2025-06-09",
      "amount": "$1,001-$15,000",
      "lateFilingFlag": false
    },
    {
      "description": "Procter & Gamble",
      "ticker": null,
      "type": "Sale",
      "date": "2025-06-09",
      "amount": "$15,001-$50,000",
      "lateFilingFlag": false
    },
    {
      "description": "VanEck Vectors Short High-Yield Municipal Index ETF",
      "ticker": "SHYD",
      "type": "Purchase",
      "date": "2025-06-13",
      "amount": "$100,001-$250,000",
      "lateFilingFlag": false
    },
    {
      "description": "Financial Select Sector SPDR Fund",
      "ticker": "XLF",
      "type": "Sale",
      "date": "2025-06-05",
      "amount": "$250,001-$500,000",
      "lateFilingFlag": false
    },
    {
      "description": "iShares Transportation Average ETF",
      "ticker": "IYT",
      "type": "Sale",
      "date": "2025-06-05",
      "amount": "$100,001-$250,000",
      "lateFilingFlag": false
    },
    {
      "description": "FNMA (Fannie Mae)",
      "ticker": null,
      "type": "Sale",
      "date": "2025-06-05",
      "amount": "$15,001-$50,000",
      "lateFilingFlag": false
    },
    {
      "description": "iShares 20+ Year Treasury Bond ETF",
      "ticker": "TLT",
      "type": "Purchase",
      "date": "2025-05-20",
      "amount": "$100,001-$250,000",
      "lateFilingFlag": false
    },
    {
      "description": "Financial Select Sector SPDR Fund",
      "ticker": "XLF",
      "type": "Sale",
      "date": "2025-05-16",
      "amount": "$15,001-$50,000",
      "lateFilingFlag": false
    },
    {
      "description": "iShares 20+ Year Treasury Bond ETF",
      "ticker": "TLT",
      "type": "Purchase",
      "date": "2025-05-16",
      "amount": "$15,001-$50,000",
      "lateFilingFlag": false
    },
    {
      "description": "FNMA (Fannie Mae)",
      "ticker": null,
      "type": "Sale",
      "date": "2025-05-16",
      "amount": "$1,001-$15,000",
      "lateFilingFlag": false
    },
    {
      "description": "S&P 500 Future, closed",
      "ticker": null,
      "type": "Sale",
      "date": "2025-05-02",
      "amount": "$250,001-$500,000",
      "lateFilingFlag": false
    },
    {
      "description": "VanEck Vectors Short High-Yield Municipal Index ETF",
      "ticker": "SHYD",
      "type": "Purchase",
      "date": "2025-04-15",
      "amount": "$100,001-$250,000",
      "lateFilingFlag": false
    },
    {
      "description": "S&P 500 futures option, opened",
      "ticker": null,
      "type": "Sale",
      "date": "2025-03-05",
      "amount": "$250,001-$500,000",
      "lateFilingFlag": false
    },
    {
      "description": "S&P 500 future, opened",
      "ticker": null,
      "type": "Purchase",
      "date": "2025-03-05",
      "amount": "$250,001-$500,000",
      "lateFilingFlag": false
    }
  ],
  "summary": "Miran reported 64 sales (est. $4.7M) and 6 purchases (est. $1.7M). Holdings included IVV, GOOGL, AMZN, BRK.B, MSFT, among others."
}